templates/category_page.jinja
templates/concept_page.jinja
templates/event.jinja
templates/event_form.jinja
templates/form_page.jinja
templates/help_page.jinja
templates/list_of_page.jinja
templates/property_page.jinja
templates/template.jinja
templates/template_page.jinja
templates/uml.jinja
templates/macros/form.jinja
templates/macros/table.jinja
templates/macros/template.jinja
templates/macros/utils.jinja
wikifile/__init__.py
wikifile/cmdline.py
wikifile/metamodel.py
wikifile/smw.py
wikifile/utils.py
wikifile/wikiExtract.py
wikifile/wikiFile.py
wikifile/wikiFileManager.py
wikifile/wikiPage.py
wikifile/wikiRender.py
wikifile/resources/metamodel/Action.json
wikifile/resources/metamodel/Context.json
wikifile/resources/metamodel/Context_properties.json
wikifile/resources/metamodel/MetaModel.json
wikifile/resources/metamodel/Property.json
wikifile/resources/metamodel/Property_properties.json
wikifile/resources/metamodel/SMW_Type.json
wikifile/resources/metamodel/SMW_Type_properties.json
wikifile/resources/metamodel/SMW_Types.json
wikifile/resources/metamodel/Topic.json
wikifile/resources/metamodel/TopicLink.json
wikifile/resources/metamodel/TopicLink_properties.json
wikifile/resources/metamodel/TopicLinks.json
wikifile/resources/metamodel/Topic_properties.json
wikirender-0.0.43.dist-info/LICENSE
wikirender-0.0.43.dist-info/METADATA
wikirender-0.0.43.dist-info/WHEEL
wikirender-0.0.43.dist-info/entry_points.txt
wikirender-0.0.43.dist-info/top_level.txt
wikirender-0.0.43.dist-info/RECORD
