Metadata-Version: 2.1
Name: wikirender
Version: 0.0.43
Summary: Convert Json data into wiki files or update existing files. Provides different templates to generate wiki files
Home-page: https://github.com/tholzheim/wikirender
Author: Tim Holzheim
Maintainer: Tim Holzheim
License: Apache License
Classifier: Programming Language :: Python
Classifier: Programming Language :: Python :: 3.8
Classifier: Programming Language :: Python :: 3.9
Classifier: Programming Language :: Python :: 3.10
License-File: LICENSE
Requires-Dist: wikitextparser
Requires-Dist: jinja2
Requires-Dist: pylodstorage (>=0.4.7)
Requires-Dist: py-3rdparty-mediawiki (>=0.8.0)
